docgen/__init__.py
docgen/description.py
docgen/run.py
docgen/system_tests.py
docgen/test_runner.py
pdd_docgen-1.0.16.dist-info/METADATA
pdd_docgen-1.0.16.dist-info/WHEEL
pdd_docgen-1.0.16.dist-info/top_level.txt
pdd_docgen-1.0.16.dist-info/RECORD
