Metadata-Version: 2.1
Name: pdd-docgen
Version: 1.0.16
Summary: The test runner which generates API documentation by running tests, and an exporter of documentation to JSON format.
Home-page: http://go.pelicandd.com/n/docgen
Author: Arseni Mourzenko
Author-email: arseni.mourzenko@pelicandd.com
License: MIT
Keywords: service api documentation
Requires-Dist: requests
